solidlab_perftest_upload/main.py
solidlab_perftest_upload-1.3.0.dist-info/LICENSE
solidlab_perftest_upload-1.3.0.dist-info/METADATA
solidlab_perftest_upload-1.3.0.dist-info/WHEEL
solidlab_perftest_upload-1.3.0.dist-info/entry_points.txt
solidlab_perftest_upload-1.3.0.dist-info/top_level.txt
solidlab_perftest_upload-1.3.0.dist-info/RECORD
